{
  "dataSources": {
    "details": [],
    "primary": {
      "data": null,
      "fields": [],
      "type": "none"
    },
    "relationships": []
  },
  "description": "",
  "id": "1769808763032",
  "importDate": "2026-01-30T21:32:43.032Z",
  "importedFrom": "TaskRecorder",
  "name": "Sales agreement classifications_changed",
  "settings": {
    "comboSelectMode": "method3",
    "delayAfterClick": 800,
    "delayAfterInput": 400,
    "delayAfterSave": 1000,
    "logVerbose": false,
    "maxRetries": 3,
    "pauseOnError": false,
    "suppressLookupWarnings": true
  },
  "steps": [
    {
      "controlName": "SystemDefinedNewButton",
      "displayText": "New",
      "fieldMapping": "",
      "id": "1769808763031_5_vcqq1",
      "type": "click",
      "value": "",
      "waitUntilHidden": false,
      "waitUntilVisible": false
    },
    {
      "controlName": "AgreementClassification_Name1",
      "displayText": "Name",
      "fieldMapping": "",
      "fieldType": {
        "allowFreetext": true,
        "controlType": "Input",
        "inputType": "lookup",
        "isLookup": true
      },
      "id": "1769808763031_9_lpj06",
      "type": "input",
      "value": "testname",
      "waitUntilHidden": false,
      "waitUntilVisible": false
    },
    {
      "controlName": "AgreementClassification_Description1",
      "displayText": "Description",
      "fieldMapping": "",
      "fieldType": {
        "allowFreetext": true,
        "controlType": "Input",
        "inputType": "lookup",
        "isLookup": true
      },
      "id": "1769808763032_13_gmtry",
      "type": "input",
      "value": "testdescription",
      "waitUntilHidden": false,
      "waitUntilVisible": false
    },
    {
      "controlName": "AgreementClassification_MatchingPolicy",
      "displayText": "",
      "fieldMapping": "",
      "fieldType": {
        "allowFreetext": true,
        "controlType": "Input",
        "inputType": "lookup",
        "isLookup": true
      },
      "id": "1769808763032_17_mu6cn",
      "type": "select",
      "value": "Two-way matching",
      "waitUntilHidden": false,
      "waitUntilVisible": false
    },
    {
      "controlName": "SystemDefinedSaveButton",
      "displayText": "Save",
      "fieldMapping": "",
      "id": "1769808763032_21_s1n7y",
      "type": "click",
      "value": "",
      "waitUntilHidden": false,
      "waitUntilVisible": false
    }
  ]
}